Workbook

Sheet Sales
A1: order_id | B1: order_date | C1: store_id | D1: product_id | E1: units | F1: unit_price | G1: discount | H1: revenue | I1: category
A2: 104321 | B2: 45658 | C2: S01 | D2: P302 | E2: 2 | F2: 24 | G2: 0 | H2: =E2*F2*(1-G2) | I2: =XLOOKUP(D2,Products!$A$2:$A$15,Products!$B$2:$B$15,"Not found")
A3: 104322 | B3: 45658 | C3: S01 | D3: P403 | E3: 1 | F3: 89 | G3: 0 | H3: =E3*F3*(1-G3) | I3: =XLOOKUP(D3,Products!$A$2:$A$15,Products!$B$2:$B$15,"Not found")
A4: 104323 | B4: 45658 | C4: S01 | D4: P102 | E4: 1 | F4: 14.5 | G4: 0 | H4: =E4*F4*(1-G4) | I4: =XLOOKUP(D4,Products!$A$2:$A$15,Products!$B$2:$B$15,"Not found")
A5: 104324 | B5: 45658 | C5: S01 | D5: P101 | E5: 2 | F5: 39 | G5: 0.1 | H5: =E5*F5*(1-G5) | I5: =XLOOKUP(D5,Products!$A$2:$A$15,Products!$B$2:$B$15,"Not found")
A6: 104325 | B6: 45658 | C6: S01 | D6: P301 | E6: 1 | F6: 119 | G6: 0.1 | H6: =E6*F6*(1-G6) | I6: =XLOOKUP(D6,Products!$A$2:$A$15,Products!$B$2:$B$15,"Not found")
A7: 104326 | B7: 45658 | C7: S02 | D7: P302 | E7: 4 | F7: 24 | G7: 0 | H7: =E7*F7*(1-G7) | I7: =XLOOKUP(D7,Products!$A$2:$A$15,Products!$B$2:$B$15,"Not found")
A8: 104327 | B8: 45658 | C8: S03 | D8: P201 | E8: 1 | F8: 149 | G8: 0 | H8: =E8*F8*(1-G8) | I8: =XLOOKUP(D8,Products!$A$2:$A$15,Products!$B$2:$B$15,"Not found")
A9: 104328 | B9: 45658 | C9: S03 | D9: P303 | E9: 3 | F9: 12 | G9: 0 | H9: =E9*F9*(1-G9) | I9: =XLOOKUP(D9,Products!$A$2:$A$15,Products!$B$2:$B$15,"Not found")
A10: 104329 | B10: 45658 | C10: S03 | D10: P102 | E10: 3 | F10: 14.5 | G10: 0 | H10: =E10*F10*(1-G10) | I10: =XLOOKUP(D10,Products!$A$2:$A$15,Products!$B$2:$B$15,"Not found")
A11: 104330 | B11: 45658 | C11: S03 | D11: P302 | E11: 3 | F11: 24 | G11: 0 | H11: =E11*F11*(1-G11) | I11: =XLOOKUP(D11,Products!$A$2:$A$15,Products!$B$2:$B$15,"Not found")
A12: 104331 | B12: 45658 | C12: S04 | D12: P102 | E12: 1 | F12: 14.5 | G12: 0 | H12: =E12*F12*(1-G12) | I12: =XLOOKUP(D12,Products!$A$2:$A$15,Products!$B$2:$B$15,"Not found")
A13: 104332 | B13: 45658 | C13: S05 | D13: P202 | E13: 4 | F13: 79 | G13: 0 | H13: =E13*F13*(1-G13) | I13: =XLOOKUP(D13,Products!$A$2:$A$15,Products!$B$2:$B$15,"Not found")
... A4572: 108891 | B4572: 46022 | C4572: S06 | D4572: P204 | E4572: 1 | F4572: 229 | G4572: 0 | H4572: =E4572*F4572*(1-G4572) | I4572: =XLOOKUP(D4572,Products!$A$2:$A$15,Products!$B$2:$B$15,"Not found")

Sheet Products
A1: product_id | B1: category | C1: product_name | D1: list_price | E1: unit_cost
A2: P101 | B2: Garden | C2: Hose 20 m | D2: 39 | E2: 18.5
A3: P102 | B3: Garden | C3: Potting mix 25 L | D3: 14.5 | E3: 6.2
A4: P103 | B4: Garden | C4: Pruning shears | D4: 29 | E4: 11
A5: P104 | B5: Garden | C5: Raised bed kit | D5: 189 | E5: 96
A6: P201 | B6: Tools | C6: Cordless drill | D6: 149 | E6: 88
A7: P202 | B7: Tools | C7: Socket set | D7: 79 | E7: 41
A8: P203 | B8: Tools | C8: Tape measure 8 m | D8: 19.5 | E8: 7.4
A9: P204 | B9: Tools | C9: Workbench | D9: 229 | E9: 131
A10: P301 | B10: Paint | C10: Interior paint 10 L | D10: 119 | E10: 63
A11: P302 | B11: Paint | C11: Roller kit | D11: 24 | E11: 9.8
A12: P303 | B12: Paint | C12: Masking tape 3-pack | D12: 12 | E12: 4.1
A13: P401 | B13: Outdoor | C13: Gas BBQ 4-burner | D13: 549 | E13: 352
... A15: P403 | B15: Outdoor | C15: Shade sail | D15: 89 | E15: 38

Sheet Stores
A1: store_id | B1: store_name | C1: state | D1: opened
A2: S01 | B2: Adelaide CBD | C2: SA | D2: 42064
A3: S02 | B3: Marion | C3: SA | D3: 42961
A4: S03 | B4: Glenelg | C4: SA | D4: 43771
A5: S04 | B5: Ballarat | C5: VIC | D5: 42510
A6: S05 | B6: Geelong | C6: VIC | D6: 44235
A7: S06 | B7: Bendigo | C7: VIC | D7: 45173

Sheet Summary
A1: store_id | B1: Garden | C1: Tools | D1: Paint | E1: Outdoor | F1: Orders 20%+ off
A2: S01 | B2: =SUMIFS(Sales!$H$2:$H$4572,Sales!$C$2:$C$4572,$A2,Sales!$I$2:$I$4572,B$1) | C2: =SUMIFS(Sales!$H$2:$H$4572,Sales!$C$2:$C$4572,$A2,Sales!$I$2:$I$4572,C$1) | D2: =SUMIFS(Sales!$H$2:$H$4572,Sales!$C$2:$C$4572,$A2,Sales!$I$2:$I$4572,D$1) | E2: =SUMIFS(Sales!$H$2:$H$4572,Sales!$C$2:$C$4572,$A2,Sales!$I$2:$I$4572,E$1) | F2: =COUNTIFS(Sales!$C$2:$C$4572,$A2,Sales!$G$2:$G$4572,">=0.2")
A3: S02 | B3: =SUMIFS(Sales!$H$2:$H$4572,Sales!$C$2:$C$4572,$A3,Sales!$I$2:$I$4572,B$1) | C3: =SUMIFS(Sales!$H$2:$H$4572,Sales!$C$2:$C$4572,$A3,Sales!$I$2:$I$4572,C$1) | D3: =SUMIFS(Sales!$H$2:$H$4572,Sales!$C$2:$C$4572,$A3,Sales!$I$2:$I$4572,D$1) | E3: =SUMIFS(Sales!$H$2:$H$4572,Sales!$C$2:$C$4572,$A3,Sales!$I$2:$I$4572,E$1) | F3: =COUNTIFS(Sales!$C$2:$C$4572,$A3,Sales!$G$2:$G$4572,">=0.2")
A4: S03 | B4: =SUMIFS(Sales!$H$2:$H$4572,Sales!$C$2:$C$4572,$A4,Sales!$I$2:$I$4572,B$1) | C4: =SUMIFS(Sales!$H$2:$H$4572,Sales!$C$2:$C$4572,$A4,Sales!$I$2:$I$4572,C$1) | D4: =SUMIFS(Sales!$H$2:$H$4572,Sales!$C$2:$C$4572,$A4,Sales!$I$2:$I$4572,D$1) | E4: =SUMIFS(Sales!$H$2:$H$4572,Sales!$C$2:$C$4572,$A4,Sales!$I$2:$I$4572,E$1) | F4: =COUNTIFS(Sales!$C$2:$C$4572,$A4,Sales!$G$2:$G$4572,">=0.2")
A5: S04 | B5: =SUMIFS(Sales!$H$2:$H$4572,Sales!$C$2:$C$4572,$A5,Sales!$I$2:$I$4572,B$1) | C5: =SUMIFS(Sales!$H$2:$H$4572,Sales!$C$2:$C$4572,$A5,Sales!$I$2:$I$4572,C$1) | D5: =SUMIFS(Sales!$H$2:$H$4572,Sales!$C$2:$C$4572,$A5,Sales!$I$2:$I$4572,D$1) | E5: =SUMIFS(Sales!$H$2:$H$4572,Sales!$C$2:$C$4572,$A5,Sales!$I$2:$I$4572,E$1) | F5: =COUNTIFS(Sales!$C$2:$C$4572,$A5,Sales!$G$2:$G$4572,">=0.2")
A6: S05 | B6: =SUMIFS(Sales!$H$2:$H$4572,Sales!$C$2:$C$4572,$A6,Sales!$I$2:$I$4572,B$1) | C6: =SUMIFS(Sales!$H$2:$H$4572,Sales!$C$2:$C$4572,$A6,Sales!$I$2:$I$4572,C$1) | D6: =SUMIFS(Sales!$H$2:$H$4572,Sales!$C$2:$C$4572,$A6,Sales!$I$2:$I$4572,D$1) | E6: =SUMIFS(Sales!$H$2:$H$4572,Sales!$C$2:$C$4572,$A6,Sales!$I$2:$I$4572,E$1) | F6: =COUNTIFS(Sales!$C$2:$C$4572,$A6,Sales!$G$2:$G$4572,">=0.2")
A7: S06 | B7: =SUMIFS(Sales!$H$2:$H$4572,Sales!$C$2:$C$4572,$A7,Sales!$I$2:$I$4572,B$1) | C7: =SUMIFS(Sales!$H$2:$H$4572,Sales!$C$2:$C$4572,$A7,Sales!$I$2:$I$4572,C$1) | D7: =SUMIFS(Sales!$H$2:$H$4572,Sales!$C$2:$C$4572,$A7,Sales!$I$2:$I$4572,D$1) | E7: =SUMIFS(Sales!$H$2:$H$4572,Sales!$C$2:$C$4572,$A7,Sales!$I$2:$I$4572,E$1) | F7: =COUNTIFS(Sales!$C$2:$C$4572,$A7,Sales!$G$2:$G$4572,">=0.2")
